kvbm/__init__.py
kvbm/_core.abi3.so
kvbm/_core.pyi
kvbm/utils.py
kvbm/trtllm_integration/__init__.py
kvbm/trtllm_integration/consolidator_config.py
kvbm/trtllm_integration/rust.py
kvbm/trtllm_integration/connector/__init__.py
kvbm/trtllm_integration/connector/kvbm_connector_leader.py
kvbm/trtllm_integration/connector/kvbm_connector_worker.py
kvbm/vllm_integration/__init__.py
kvbm/vllm_integration/connector_leader.py
kvbm/vllm_integration/connector_worker.py
kvbm/vllm_integration/consolidator_config.py
kvbm/vllm_integration/kv_cache_manager.py
kvbm/vllm_integration/kv_cache_utils.py
kvbm/vllm_integration/rust.py
kvbm/vllm_integration/connector/__init__.py
kvbm/vllm_integration/connector/dynamo_connector.py
kvbm/vllm_integration/connector/pd_connector.py
kvbm-0.8.1.dist-info/METADATA
kvbm-0.8.1.dist-info/WHEEL
kvbm-0.8.1.dist-info/RECORD
kvbm-0.8.1.dist-info/licenses/LICENSE
