Metadata-Version: 2.4
Name: kvbm
Version: 0.8.1
Classifier: Development Status :: 4 - Beta
Classifier: Intended Audience :: Developers
Classifier: Intended Audience :: Science/Research
Classifier: Intended Audience :: Information Technology
Classifier: License :: OSI Approved :: Apache Software License
Classifier: Programming Language :: Python :: 3.10
Classifier: Programming Language :: Python :: 3.11
Classifier: Programming Language :: Python :: 3.12
Classifier: Topic :: Scientific/Engineering
Classifier: Topic :: Scientific/Engineering :: Artificial Intelligence
Classifier: Operating System :: POSIX :: Linux
Requires-Dist: nixl[cu12]==0.8.0
Requires-Dist: pydantic>=2.0
Requires-Dist: nixl[cu12]==0.8.0 ; extra == 'cu12'
Requires-Dist: nixl[cu13]==0.8.0 ; extra == 'cu13'
Requires-Dist: kvbm[test] ; extra == 'dev'
Requires-Dist: maturin>=1.0,<2.0 ; extra == 'dev'
Requires-Dist: patchelf ; extra == 'dev'
Requires-Dist: pytest>=8.3.4 ; extra == 'test'
Requires-Dist: pytest-mypy ; extra == 'test'
Requires-Dist: pytest-asyncio ; extra == 'test'
Provides-Extra: cu12
Provides-Extra: cu13
Provides-Extra: dev
Provides-Extra: test
License-File: LICENSE
Summary: Dynamo KVBM
Keywords: llm,genai,inference,nvidia,kvcache,dynamo
Home-Page: https://github.com/ai-dynamo/dynamo
Author-email: "NVIDIA Inc." <sw-dl-dynamo@nvidia.com>
License: Apache-2.0
Requires-Python: >=3.10
